{"status": "ok", "data": {"aqi": 47, "idx": 5508, "attributions": [{"url": "https://www.airkorea.or.kr/", "name": "South Air Korea Environment Corporation (\ub300\uae30\uc624\uc5fc\uc2e4\uc2dc\uac04\uacf5\uac1c\uc2dc\uc2a4\ud15c)", "logo": "SouthKorea-AirKorea.png"}, {"url": "http://cleanair.seoul.go.kr/", "name": "Seoul Clean Air Pollution Information (\uc11c\uc6b8\ud2b9\ubcc4\uc2dc \uae30\ud6c4\ub300\uae30\ud658\uacbd\uc815\ubcf4)", "logo": "SouthKorea-Seoul.png"}, {"url": "https://waqi.info/", "name": "World Air Quality Index Project"}], "city": {"geo": [37.566535, 126.9779692], "name": "Seoul (\uc11c\uc6b8)", "url": "https://aqicn.org/city/seoul", "location": ""}, "dominentpol": "o3", "iaqi": {"co": {"v": 4.2}, "h": {"v": 45.8}, "no2": {"v": 12}, "o3": {"v": 47}, "p": {"v": 997}, "pm10": {"v": 13}, "pm25": {"v": 30}, "r": {"v": 99.3}, "so2": {"v": 4.3}, "t": {"v": 32.8}, "w": {"v": 2.5}}, "time": {"s": "2024-08-28 17:00:00", "tz": "+09:00", "v": 1724864400, "iso": "2024-08-28T17:00:00+09:00"}, "forecast": {"daily": {"o3": [{"avg": 4, "day": "2024-08-26", "max": 18, "min": 1}, {"avg": 5, "day": "2024-08-27", "max": 41, "min": 1}, {"avg": 11, "day": "2024-08-28", "max": 31, "min": 1}, {"avg": 10, "day": "2024-08-29", "max": 24, "min": 2}, {"avg": 7, "day": "2024-08-30", "max": 29, "min": 2}, {"avg": 7, "day": "2024-08-31", "max": 37, "min": 1}, {"avg": 5, "day": "2024-09-01", "max": 32, "min": 1}, {"avg": 1, "day": "2024-09-02", "max": 1, "min": 1}], "pm10": [{"avg": 40, "day": "2024-08-27", "max": 46, "min": 32}, {"avg": 30, "day": "2024-08-28", "max": 46, "min": 19}, {"avg": 21, "day": "2024-08-29", "max": 28, "min": 10}, {"avg": 16, "day": "2024-08-30", "max": 22, "min": 8}, {"avg": 28, "day": "2024-08-31", "max": 52, "min": 12}, {"avg": 25, "day": "2024-09-01", "max": 31, "min": 18}, {"avg": 28, "day": "2024-09-02", "max": 37, "min": 16}, {"avg": 17, "day": "2024-09-03", "max": 28, "min": 10}], "pm25": [{"avg": 92, "day": "2024-08-27", "max": 111, "min": 84}, {"avg": 94, "day": "2024-08-28", "max": 138, "min": 68}, {"avg": 65, "day": "2024-08-29", "max": 89, "min": 42}, {"avg": 55, "day": "2024-08-30", "max": 75, "min": 30}, {"avg": 82, "day": "2024-08-31", "max": 152, "min": 44}, {"avg": 71, "day": "2024-09-01", "max": 81, "min": 48}, {"avg": 83, "day": "2024-09-02", "max": 111, "min": 48}, {"avg": 45, "day": "2024-09-03", "max": 68, "min": 21}], "uvi": [{"avg": 0, "day": "2024-08-27", "max": 0, "min": 0}, {"avg": 1, "day": "2024-08-28", "max": 8, "min": 0}, {"avg": 1, "day": "2024-08-29", "max": 8, "min": 0}, {"avg": 1, "day": "2024-08-30", "max": 7, "min": 0}, {"avg": 1, "day": "2024-08-31", "max": 7, "min": 0}, {"avg": 2, "day": "2024-09-01", "max": 7, "min": 0}]}}, "debug": {"sync": "2024-08-28T17:29:12+09:00"}}}
